w2gpu-0.1.0.dist-info/METADATA
w2gpu-0.1.0.dist-info/WHEEL
w2gpu/__init__.py
w2gpu/w2gpu.cpython-313-darwin.so
w2gpu-0.1.0.dist-info/RECORD
