Metadata-Version: 2.4
Name: w2gpu
Version: 0.1.0
Classifier: Programming Language :: Rust
Classifier: Programming Language :: Python :: Implementation :: CPython
Classifier: Programming Language :: Python :: Implementation :: PyPy
Summary: WASM-to-WGSL
License: CC0-1.0
Requires-Python: >=3.8
